.gitattributes
.gitignore
.pre-commit-config.yaml
CHANGELOG.md
LICENSE
MANIFEST.in
README.md
environment.yml
pyproject.toml
.github/workflows/ci.yml
docs/Makefile
docs/make.bat
docs/source/conf.py
docs/source/index.rst
src/ritas/__init__.py
src/ritas/cli.py
src/ritas/io.py
src/ritas/main.py
src/ritas/polygons.py
src/ritas/utils.py
src/ritas/viz.py
src/ritas/workflows.py
src/ritas.egg-info/PKG-INFO
src/ritas.egg-info/SOURCES.txt
src/ritas.egg-info/dependency_links.txt
src/ritas.egg-info/entry_points.txt
src/ritas.egg-info/requires.txt
src/ritas.egg-info/top_level.txt
src/ritas/app/__init__.py
src/ritas/app/app.py
src/ritas/app/.streamlit/config.toml
tests/__init__.py
tests/test_cli.py
tests/test_polygons.py
tests/data/square_100m.csv