Metadata-Version: 2.1
Name: ritas
Version: 0.4.0
License: MIT License
Classifier: Programming Language :: Python :: 3 :: Only
Classifier: Programming Language :: Python :: 3.9
Classifier: Programming Language :: Python :: 3.10
Classifier: Programming Language :: Python :: 3.11
Classifier: Programming Language :: Python :: 3.12
Classifier: Programming Language :: Python :: 3.13
Requires-Python: >=3.9
License-File: LICENSE
Requires-Dist: click
Requires-Dist: geopandas
Requires-Dist: matplotlib
Requires-Dist: pandas
Requires-Dist: pyarrow
Requires-Dist: pykrige
Requires-Dist: pyproj
Requires-Dist: rasterio>=1.4
Requires-Dist: shapely
Requires-Dist: streamlit
Requires-Dist: tqdm
